ga4mp/__init__.py
ga4mp/event.py
ga4mp/ga4mp.py
ga4mp/item.py
ga4mp/store.py
ga4mp/utils.py
ga4mp-2.0.4.dist-info/LICENSE
ga4mp-2.0.4.dist-info/WHEEL
ga4mp-2.0.4.dist-info/METADATA
ga4mp-2.0.4.dist-info/RECORD
