Metadata-Version: 2.1
Name: ga4mp
Version: 2.0.4
Summary: Google Analytics 4 Measurement Protocol Python Module
Home-page: https://github.com/adswerve/GA4-Measurement-Protocol-Python
License: BSD
Author: Adswerve
Author-email: analytics-help@adswerve.com
Requires-Python: >=3.6,<4.0
Classifier: License :: Other/Proprietary License
Classifier: Programming Language :: Python :: 3
Classifier: Programming Language :: Python :: 3.6
Classifier: Programming Language :: Python :: 3.7
Classifier: Programming Language :: Python :: 3.8
Classifier: Programming Language :: Python :: 3.9
Classifier: Programming Language :: Python :: 3.10
Project-URL: Repository, https://github.com/adswerve/GA4-Measurement-Protocol-Python
